README.md
setup.cfg
setup.py
pyicam/__init__.py
pyicam.egg-info/PKG-INFO
pyicam.egg-info/SOURCES.txt
pyicam.egg-info/dependency_links.txt
pyicam.egg-info/requires.txt
pyicam.egg-info/top_level.txt
pyicam/saml/__init__.py
pyicam/saml/metadata.py
pyicam/saml/sso.py
pyicam/saml/test.py