Metadata-Version: 1.1
Name: pyicam
Version: 0.1.0rc2
Summary: SAML 2.0 client authentication library
Home-page: https://github.com/nwfsc-data/PyICAM
Author: NOAA Northwest science Fishery Resource Analysis and Montoring (FRAM) Data team
Author-email: nwfsc.fram.data@noaa.gov
License: CC0-1.0
Keywords: saml saml2 sso icam noaa
Platform: UNKNOWN
Classifier: Development Status :: 3 - Alpha
Classifier: Intended Audience :: Developers
Classifier: Intended Audience :: System Administrators
Classifier: Topic :: Software Development :: Libraries :: Python Modules
Classifier: Topic :: System :: Systems Administration :: Authentication/Directory
Classifier: License :: CC0 1.0 Universal (CC0 1.0) Public Domain Dedication
Classifier: Programming Language :: Python :: 3
Classifier: Programming Language :: Python :: 3.3
Classifier: Programming Language :: Python :: 3.4
Classifier: Programming Language :: Python :: 3.5
Classifier: Programming Language :: Python :: 3.6
